testcase_generator/__init__.py
testcase_generator/parser.py
testcase_generator/generators/__init__.py
testcase_generator/generators/array_generator.py
testcase_generator/generators/collection_generator.py
testcase_generator/generators/custom_generator.py
testcase_generator/generators/graph_generator.py
testcase_generator/generators/string_generator.py
testcase_generator/models/__init__.py
testcase_generator/models/constraints.py
testcase_generator/models/models.py
testcase_generator-0.3.1.dist-info/LICENSE
testcase_generator-0.3.1.dist-info/METADATA
testcase_generator-0.3.1.dist-info/WHEEL
testcase_generator-0.3.1.dist-info/top_level.txt
testcase_generator-0.3.1.dist-info/RECORD
