Metadata-Version: 2.1
Name: testcase-generator
Version: 0.3.1
Summary: A testcase generator for creating testcases for online judges.
Home-page: https://github.com/Ninjaclasher/testcase-generator
Author: Evan Zhang
License: UNKNOWN
Platform: UNKNOWN
Classifier: Development Status :: 3 - Alpha
Classifier: Environment :: Console
Classifier: Intended Audience :: Developers
Classifier: License :: OSI Approved :: GNU Affero General Public License v3 or later (AGPLv3+)
Classifier: Operating System :: POSIX :: Linux
Classifier: Programming Language :: Python
Classifier: Programming Language :: Python :: 3.7
Requires-Dist: pyyaml
